{"00:00:51": {"Terminal 2": 1, "Terminal 5D": 1, "Terminal 5F": 1}, "00:02:41": {"Terminal 2": 1, "Terminal 5D": 1, "Terminal 5F": 1}, "00:04:32": {"Terminal 2": 1, "Terminal 5D": 1, "Terminal 5F": 1}, "00:11:48": {"Terminal 2": 1, "Terminal 5D": 1, "Terminal 5F": 1}, "00:13:45": {"Terminal 2": 1, "Terminal 5D": 1, "Terminal 5F": 1}, "00:15:34": {"Terminal 2": 1, "Terminal 5D": 1, "Terminal 5F": 1}, "00:17:27": {"Terminal 2": 1, "Terminal 5D": 1, "Terminal 5F": 1}, "00:19:17": {"Terminal 2": 1, "Terminal 5D": 1, "Terminal 5F": 1}, "00:21:07": {"Terminal 2": 1, "Terminal 5D": 1, "Terminal 5F": 1}, "00:22:57": {"Terminal 2": 1, "Terminal 5D": 1, "Terminal 5F": 1}, "00:24:47": {"Terminal 2": 1, "Terminal 5D": 1, "Terminal 5F": 1}, "00:26:36": {"Terminal 2": 1, "Terminal 5D": 1, "Terminal 5F": 1}, "00:28:26": {"Terminal 2": 1, "Terminal 5D": 1, "Terminal 5F": 1}, "00:30:15": {"Terminal 2": 1, "Terminal 5D": 1, "Terminal 5F": 1}, "00:32:06": {"Terminal 2": 1, "Terminal 5D": 1, "Terminal 5F": 1}, "00:33:57": {"Terminal 2": 1, "Terminal 5D": 1, "Terminal 5F": 1}, "00:35:46": {"Terminal 2": 1, "Terminal 5D": 1, "Terminal 5F": 1}, "00:37:37": {"Terminal 2": 1, "Terminal 5D": 1, "Terminal 5F": 1}, "00:39:28": {"Terminal 2": 1, "Terminal 5D": 1, "Terminal 5F": 1}, "00:41:19": {"Terminal 2": 1, "Terminal 5D": 1, "Terminal 5F": 1}, "00:43:08": {"Terminal 2": 1, "Terminal 5D": 1, "Terminal 5F": 1}, "00:44:58": {"Terminal 2": 1, "Terminal 5D": 1, "Terminal 5F": 1}, "00:46:50": {"Terminal 2": 1, "Terminal 5D": 1, "Terminal 5F": 1}, "00:48:40": {"Terminal 2": 1, "Terminal 5D": 1, "Terminal 5F": 1}, "00:50:30": {"Terminal 2": 1, "Terminal 5D": 1, "Terminal 5F": 1}, "00:52:21": {"Terminal 2": 1, "Terminal 5D": 1, "Terminal 5F": 1}, "00:54:11": {"Terminal 2": 1, "Terminal 5D": 1, "Terminal 5F": 1}, "00:56:02": {"Terminal 2": 1, "Terminal 5D": 1, "Terminal 5F": 1}, "00:57:53": {"Terminal 2": 1, "Terminal 5D": 1, "Terminal 5F": 1}, "00:59:43": {"Terminal 2": 1, "Terminal 5D": 1, "Terminal 5F": 1}, "01:01:33": {"Terminal 2": 1, "Terminal 5D": 1, "Terminal 5F": 1}, "01:03:22": {"Terminal 2": 1, "Terminal 5D": 1, "Terminal 5F": 1}, "01:05:11": {"Terminal 2": 1, "Terminal 5D": 1, "Terminal 5F": 1}, "01:06:59": {"Terminal 2": 1, "Terminal 5D": 1, "Terminal 5F": 1}, "01:08:48": {"Terminal 2": 1, "Terminal 5D": 1, "Terminal 5F": 1}, "01:10:38": {"Terminal 2": 1, "Terminal 5D": 1, "Terminal 5F": 1}, "01:12:28": {"Terminal 2": 1, "Terminal 5D": 1, "Terminal 5F": 1}, "01:14:18": {"Terminal 2": 1, "Terminal 5D": 1, "Terminal 5F": 1}, "01:16:12": {"Terminal 2": 1, "Terminal 5D": 1, "Terminal 5F": 1}, "01:18:02": {"Terminal 2": 1, "Terminal 5D": 1, "Terminal 5F": 1}, "01:19:51": {"Terminal 2": 1, "Terminal 5D": 1, "Terminal 5F": 1}, "01:21:39": {"Terminal 2": 1, "Terminal 5D": 1, "Terminal 5F": 1}, "01:23:28": {"Terminal 2": 1, "Terminal 5D": 1, "Terminal 5F": 1}, "01:25:18": {"Terminal 2": 1, "Terminal 5D": 1, "Terminal 5F": 1}, "01:27:10": {"Terminal 2": 1, "Terminal 5D": 1, "Terminal 5F": 1}, "01:28:58": {"Terminal 2": 1, "Terminal 5D": 1, "Terminal 5F": 1}, "01:30:46": {"Terminal 2": 1, "Terminal 5D": 1, "Terminal 5F": 1}, "01:32:34": {"Terminal 2": 1, "Terminal 5D": 1, "Terminal 5F": 2}, "01:34:25": {"Terminal 2": 1, "Terminal 5D": 1, "Terminal 5F": 1}, "01:36:15": {"Terminal 2": 1, "Terminal 5D": 1, "Terminal 5F": 1}, "01:38:07": {"Terminal 2": 1, "Terminal 5D": 1, "Terminal 5F": 1}, "01:39:58": {"Terminal 2": 1, "Terminal 5D": 1, "Terminal 5F": 2}, "01:41:48": {"Terminal 2": 1, "Terminal 5D": 1, "Terminal 5F": 2}, "01:43:38": {"Terminal 2": 1, "Terminal 5D": 1, "Terminal 5F": 1}, "01:45:27": {"Terminal 2": 1, "Terminal 5D": 1, "Terminal 5F": 3}, "01:47:17": {"Terminal 2": 1, "Terminal 5D": 1, "Terminal 5F": 2}, "01:49:07": {"Terminal 2": 1, "Terminal 5D": 1, "Terminal 5F": 3}, "01:50:57": {"Terminal 2": 1, "Terminal 5D": 1, "Terminal 5F": 5}, "01:52:49": {"Terminal 2": 1, "Terminal 5D": 1, "Terminal 5F": 5}, "01:54:39": {"Terminal 2": 1, "Terminal 5D": 1, "Terminal 5F": 4}, "01:56:29": {"Terminal 2": 1, "Terminal 5D": 1, "Terminal 5F": 4}, "01:58:19": {"Terminal 2": 1, "Terminal 5D": 1, "Terminal 5F": 4}, "02:00:08": {"Terminal 2": 1, "Terminal 5D": 1, "Terminal 5F": 8}, "02:01:58": {"Terminal 2": 1, "Terminal 5D": 1, "Terminal 5F": 9}, "02:03:48": {"Terminal 2": 1, "Terminal 5D": 1, "Terminal 5F": 8}, "02:05:39": {"Terminal 2": 1, "Terminal 5D": 1, "Terminal 5F": 10}, "02:07:27": {"Terminal 2": 1, "Terminal 5D": 1, "Terminal 5F": 10}, "02:09:16": {"Terminal 2": 1, "Terminal 5D": 1, "Terminal 5F": 15}, "02:11:07": {"Terminal 2": 1, "Terminal 5D": 1, "Terminal 5F": 15}, "02:13:00": {"Terminal 2": 1, "Terminal 5D": 1, "Terminal 5F": 12}, "02:14:51": {"Terminal 2": 1, "Terminal 5D": 1, "Terminal 5F": 13}, "02:16:40": {"Terminal 2": 1, "Terminal 5D": 1, "Terminal 5F": 12}, "02:18:30": {"Terminal 2": 1, "Terminal 5D": 1, "Terminal 5F": 9}, "02:20:20": {"Terminal 2": 1, "Terminal 5D": 1, "Terminal 5F": 8}, "02:22:10": {"Terminal 2": 1, "Terminal 5D": 1, "Terminal 5F": 6}, "02:24:00": {"Terminal 2": 1, "Terminal 5D": 1, "Terminal 5F": 7}, "02:25:50": {"Terminal 2": 1, "Terminal 5D": 1, "Terminal 5F": 6}, "02:27:40": {"Terminal 2": 1, "Terminal 5D": 1, "Terminal 5F": 2}, "02:29:32": {"Terminal 2": 1, "Terminal 5D": 1, "Terminal 5F": 2}, "02:31:24": {"Terminal 2": 1, "Terminal 5D": 1, "Terminal 5F": 1}, "02:33:14": {"Terminal 2": 1, "Terminal 5D": 1, "Terminal 5F": 1}, "02:35:04": {"Terminal 2": 1, "Terminal 5D": 1, "Terminal 5F": 1}, "02:36:53": {"Terminal 2": 1, "Terminal 5D": 1, "Terminal 5F": 1}, "02:38:44": {"Terminal 2": 1, "Terminal 5D": 1, "Terminal 5F": 1}, "02:40:34": {"Terminal 2": 1, "Terminal 5D": 1, "Terminal 5F": 1}, "02:42:24": {"Terminal 2": 1, "Terminal 5D": 1, "Terminal 5F": 1}, "02:44:12": {"Terminal 2": 1, "Terminal 5D": 1, "Terminal 5F": 1}, "02:46:02": {"Terminal 2": 1, "Terminal 5D": 1, "Terminal 5F": 1}, "02:47:49": {"Terminal 2": 1, "Terminal 5D": 1, "Terminal 5F": 1}, "02:49:40": {"Terminal 2": 1, "Terminal 5D": 1, "Terminal 5F": 1}, "02:51:31": {"Terminal 2": 1, "Terminal 5D": 1, "Terminal 5F": 1}, "02:53:21": {"Terminal 2": 1, "Terminal 5D": 1, "Terminal 5F": 1}, "02:55:10": {"Terminal 2": 1, "Terminal 5D": 1, "Terminal 5F": 1}, "02:57:00": {"Terminal 2": 1, "Terminal 5D": 1, "Terminal 5F": 1}, "02:58:50": {"Terminal 2": 1, "Terminal 5D": 1, "Terminal 5F": 1}, "03:00:40": {"Terminal 2": 1, "Terminal 5D": 1, "Terminal 5F": 1}, "03:02:30": {"Terminal 2": 1, "Terminal 5D": 1, "Terminal 5F": 1}, "03:04:20": {"Terminal 2": 1, "Terminal 5D": 1, "Terminal 5F": 1}, "03:06:08": {"Terminal 2": 1, "Terminal 5D": 1, "Terminal 5F": 1}, "03:07:56": {"Terminal 2": 1, "Terminal 5D": 1, "Terminal 5F": 1}, "03:09:47": {"Terminal 2": 1, "Terminal 5D": 1, "Terminal 5F": 1}, "03:11:38": {"Terminal 2": 1, "Terminal 5D": 1, "Terminal 5F": 1}, "03:13:27": {"Terminal 2": 1, "Terminal 5D": 1, "Terminal 5F": 1}, "03:15:18": {"Terminal 2": 1, "Terminal 5D": 1, "Terminal 5F": 1}, "03:17:07": {"Terminal 2": 1, "Terminal 5D": 1, "Terminal 5F": 2}, "03:18:56": {"Terminal 2": 1, "Terminal 5D": 1, "Terminal 5F": 3}, "03:20:47": {"Terminal 2": 1, "Terminal 5D": 1, "Terminal 5F": 7}, "03:22:37": {"Terminal 2": 1, "Terminal 5D": 2, "Terminal 5F": 5}, "03:24:29": {"Terminal 2": 1, "Terminal 5D": 7, "Terminal 5F": 6}, "03:26:20": {"Terminal 2": 1, "Terminal 5D": 18, "Terminal 5F": 6}, "03:28:12": {"Terminal 2": 1, "Terminal 5D": 6, "Terminal 5F": 6}, "03:30:01": {"Terminal 2": 1, "Terminal 5D": 9, "Terminal 5F": 7}, "03:31:51": {"Terminal 2": 1, "Terminal 5D": 10, "Terminal 5F": 11}, "03:33:41": {"Terminal 2": 1, "Terminal 5D": 10, "Terminal 5F": 13}, "03:35:31": {"Terminal 2": 1, "Terminal 5D": 11, "Terminal 5F": 18}, "03:37:20": {"Terminal 2": 1, "Terminal 5D": 13, "Terminal 5F": 45}, "03:39:09": {"Terminal 2": 1, "Terminal 5D": 14, "Terminal 5F": 45}, "03:40:59": {"Terminal 2": 1, "Terminal 5D": 19, "Terminal 5F": 45}, "03:42:48": {"Terminal 2": 1, "Terminal 5D": 20, "Terminal 5F": 45}, "03:44:38": {"Terminal 2": 1, "Terminal 5D": 21, "Terminal 5F": 45}, "03:46:30": {"Terminal 2": 1, "Terminal 5D": 13, "Terminal 5F": 45}, "03:48:20": {"Terminal 2": 1, "Terminal 5D": 14, "Terminal 5F": 45}, "03:50:11": {"Terminal 2": 1, "Terminal 5D": 23, "Terminal 5F": 45}, "03:52:01": {"Terminal 2": 1, "Terminal 5D": 23, "Terminal 5F": 45}, "03:53:51": {"Terminal 2": 1, "Terminal 5D": 19, "Terminal 5F": 45}, "03:55:42": {"Terminal 2": 1, "Terminal 5D": 25, "Terminal 5F": 45}, "03:57:32": {"Terminal 2": 1, "Terminal 5D": 20, "Terminal 5F": 45}, "03:59:21": {"Terminal 2": 1, "Terminal 5D": 16, "Terminal 5F": 45}, "04:01:05": {"Terminal 2": 45, "Terminal 5D": 45, "Terminal 5F": 45}, "04:02:52": {"Terminal 2": 1, "Terminal 5D": 16, "Terminal 5F": 45}, "04:04:42": {"Terminal 2": 1, "Terminal 5D": 45, "Terminal 5F": 45}, "04:06:34": {"Terminal 2": 1, "Terminal 5D": 45, "Terminal 5F": 45}, "04:08:24": {"Terminal 2": 1, "Terminal 5D": 13, "Terminal 5F": 45}, "04:10:13": {"Terminal 2": 1, "Terminal 5D": 13, "Terminal 5F": 45}, "04:12:04": {"Terminal 2": 2, "Terminal 5D": 13, "Terminal 5F": 45}, "04:13:54": {"Terminal 2": 6, "Terminal 5D": 12, "Terminal 5F": 45}, "04:15:45": {"Terminal 2": 6, "Terminal 5D": 11, "Terminal 5F": 45}, "04:17:33": {"Terminal 2": 6, "Terminal 5D": 12, "Terminal 5F": 45}, "04:19:24": {"Terminal 2": 5, "Terminal 5D": 14, "Terminal 5F": 45}, "04:21:15": {"Terminal 2": 6, "Terminal 5D": 13, "Terminal 5F": 45}, "04:23:03": {"Terminal 2": 6, "Terminal 5D": 12, "Terminal 5F": 45}, "04:24:54": {"Terminal 2": 10, "Terminal 5D": 45, "Terminal 5F": 45}, "04:26:43": {"Terminal 2": 8, "Terminal 5D": 45, "Terminal 5F": 45}, "04:28:33": {"Terminal 2": 7, "Terminal 5D": 45, "Terminal 5F": 45}, "04:30:22": {"Terminal 2": 7, "Terminal 5D": 45, "Terminal 5F": 45}, "04:32:12": {"Terminal 2": 7, "Terminal 5D": 45, "Terminal 5F": 45}, "04:34:02": {"Terminal 2": 9, "Terminal 5D": 45, "Terminal 5F": 45}, "04:35:53": {"Terminal 2": 10, "Terminal 5D": 45, "Terminal 5F": 45}, "04:37:43": {"Terminal 2": 12, "Terminal 5D": 45, "Terminal 5F": 45}, "04:39:33": {"Terminal 2": 12, "Terminal 5D": 45, "Terminal 5F": 45}, "04:41:23": {"Terminal 2": 16, "Terminal 5D": 45, "Terminal 5F": 45}, "04:43:13": {"Terminal 2": 20, "Terminal 5D": 45, "Terminal 5F": 45}, "04:45:07": {"Terminal 2": 22, "Terminal 5D": 45, "Terminal 5F": 45}, "04:46:59": {"Terminal 2": 23, "Terminal 5D": 45, "Terminal 5F": 45}, "04:48:50": {"Terminal 2": 24, "Terminal 5D": 45, "Terminal 5F": 45}, "04:50:40": {"Terminal 2": 22, "Terminal 5D": 45, "Terminal 5F": 45}, "04:52:32": {"Terminal 2": 24, "Terminal 5D": 45, "Terminal 5F": 45}, "04:54:22": {"Terminal 2": 26, "Terminal 5D": 45, "Terminal 5F": 45}, "04:56:12": {"Terminal 2": 26, "Terminal 5D": 45, "Terminal 5F": 45}, "04:58:04": {"Terminal 2": 24, "Terminal 5D": 45, "Terminal 5F": 45}, "04:59:53": {"Terminal 2": 23, "Terminal 5D": 45, "Terminal 5F": 45}, "05:01:42": {"Terminal 2": 24, "Terminal 5D": 45, "Terminal 5F": 45}, "05:03:34": {"Terminal 2": 25, "Terminal 5D": 45, "Terminal 5F": 45}, "05:05:23": {"Terminal 2": 26, "Terminal 5D": 45, "Terminal 5F": 45}, "05:07:14": {"Terminal 2": 26, "Terminal 5D": 45, "Terminal 5F": 45}, "05:09:03": {"Terminal 2": 27, "Terminal 5D": 45, "Terminal 5F": 45}, "05:10:54": {"Terminal 2": 24, "Terminal 5D": 45, "Terminal 5F": 45}, "05:12:43": {"Terminal 2": 23, "Terminal 5D": 45, "Terminal 5F": 45}, "05:14:34": {"Terminal 2": 24, "Terminal 5D": 45, "Terminal 5F": 45}, "05:16:24": {"Terminal 2": 24, "Terminal 5D": 45, "Terminal 5F": 45}, "05:18:14": {"Terminal 2": 24, "Terminal 5D": 45, "Terminal 5F": 45}, "05:20:02": {"Terminal 2": 25, "Terminal 5D": 45, "Terminal 5F": 45}, "05:21:54": {"Terminal 2": 27, "Terminal 5D": 45, "Terminal 5F": 45}, "05:23:43": {"Terminal 2": 27, "Terminal 5D": 45, "Terminal 5F": 45}, "05:25:35": {"Terminal 2": 26, "Terminal 5D": 45, "Terminal 5F": 45}, "05:27:24": {"Terminal 2": 24, "Terminal 5D": 45, "Terminal 5F": 45}, "05:29:15": {"Terminal 2": 25, "Terminal 5D": 45, "Terminal 5F": 45}, "05:31:05": {"Terminal 2": 25, "Terminal 5D": 45, "Terminal 5F": 45}, "05:32:55": {"Terminal 2": 20, "Terminal 5D": 45, "Terminal 5F": 45}, "05:34:45": {"Terminal 2": 24, "Terminal 5D": 45, "Terminal 5F": 45}, "05:36:34": {"Terminal 2": 22, "Terminal 5D": 45, "Terminal 5F": 45}, "05:38:24": {"Terminal 2": 21, "Terminal 5D": 45, "Terminal 5F": 45}, "05:40:14": {"Terminal 2": 23, "Terminal 5D": 45, "Terminal 5F": 45}, "05:42:06": {"Terminal 2": 25, "Terminal 5D": 45, "Terminal 5F": 45}, "05:43:55": {"Terminal 2": 22, "Terminal 5D": 45, "Terminal 5F": 45}, "05:45:45": {"Terminal 2": 24, "Terminal 5D": 45, "Terminal 5F": 45}, "05:47:32": {"Terminal 2": 23, "Terminal 5D": 45, "Terminal 5F": 45}, "05:49:22": {"Terminal 2": 23, "Terminal 5D": 45, "Terminal 5F": 45}, "05:51:13": {"Terminal 2": 21, "Terminal 5D": 45, "Terminal 5F": 45}, "05:53:02": {"Terminal 2": 18, "Terminal 5D": 45, "Terminal 5F": 45}, "05:54:51": {"Terminal 2": 18, "Terminal 5D": 45, "Terminal 5F": 45}, "05:56:41": {"Terminal 2": 20, "Terminal 5D": 45, "Terminal 5F": 45}, "05:58:29": {"Terminal 2": 18, "Terminal 5D": 45, "Terminal 5F": 45}, "06:00:21": {"Terminal 2": 17, "Terminal 5D": 45, "Terminal 5F": 45}, "06:02:11": {"Terminal 2": 14, "Terminal 5D": 45, "Terminal 5F": 45}, "06:04:01": {"Terminal 2": 6, "Terminal 5D": 45, "Terminal 5F": 45}, "06:05:51": {"Terminal 2": 3, "Terminal 5D": 45, "Terminal 5F": 45}, "06:07:42": {"Terminal 2": 1, "Terminal 5D": 45, "Terminal 5F": 45}, "06:09:33": {"Terminal 2": 1, "Terminal 5D": 45, "Terminal 5F": 45}, "06:11:23": {"Terminal 2": 1, "Terminal 5D": 45, "Terminal 5F": 45}, "06:13:14": {"Terminal 2": 1, "Terminal 5D": 45, "Terminal 5F": 45}, "06:15:03": {"Terminal 2": 1, "Terminal 5D": 11, "Terminal 5F": 45}, "06:16:53": {"Terminal 2": 1, "Terminal 5D": 10, "Terminal 5F": 45}, "06:18:46": {"Terminal 2": 1, "Terminal 5D": 11, "Terminal 5F": 45}, "06:20:36": {"Terminal 2": 1, "Terminal 5D": 10, "Terminal 5F": 45}, "06:22:26": {"Terminal 2": 1, "Terminal 5D": 8, "Terminal 5F": 45}, "06:24:18": {"Terminal 2": 1, "Terminal 5D": 7, "Terminal 5F": 45}, "06:26:09": {"Terminal 2": 1, "Terminal 5D": 6, "Terminal 5F": 45}, "06:28:02": {"Terminal 2": 1, "Terminal 5D": 7, "Terminal 5F": 45}, "06:29:54": {"Terminal 2": 1, "Terminal 5D": 7, "Terminal 5F": 45}, "06:31:44": {"Terminal 2": 1, "Terminal 5D": 5, "Terminal 5F": 45}, "06:33:36": {"Terminal 2": 1, "Terminal 5D": 6, "Terminal 5F": 45}, "06:35:25": {"Terminal 2": 1, "Terminal 5D": 6, "Terminal 5F": 8}, "06:37:17": {"Terminal 2": 1, "Terminal 5D": 7, "Terminal 5F": 7}, "06:39:08": {"Terminal 2": 1, "Terminal 5D": 5, "Terminal 5F": 5}, "06:41:02": {"Terminal 2": 1, "Terminal 5D": 4, "Terminal 5F": 3}, "06:42:52": {"Terminal 2": 1, "Terminal 5D": 4, "Terminal 5F": 3}, "06:44:42": {"Terminal 2": 1, "Terminal 5D": 4, "Terminal 5F": 2}, "06:46:33": {"Terminal 2": 1, "Terminal 5D": 4, "Terminal 5F": 2}, "06:48:21": {"Terminal 2": 1, "Terminal 5D": 2, "Terminal 5F": 2}, "06:50:21": {"Terminal 2": 1, "Terminal 5D": 4, "Terminal 5F": 3}, "06:52:11": {"Terminal 2": 1, "Terminal 5D": 3, "Terminal 5F": 2}, "06:54:01": {"Terminal 2": 1, "Terminal 5D": 4, "Terminal 5F": 1}, "06:55:51": {"Terminal 2": 1, "Terminal 5D": 4, "Terminal 5F": 2}, "06:57:43": {"Terminal 2": 1, "Terminal 5D": 2, "Terminal 5F": 2}, "06:59:32": {"Terminal 2": 1, "Terminal 5D": 2, "Terminal 5F": 4}, "07:01:22": {"Terminal 2": 1, "Terminal 5D": 2, "Terminal 5F": 4}, "07:03:11": {"Terminal 2": 1, "Terminal 5D": 1, "Terminal 5F": 4}, "07:05:01": {"Terminal 2": 1, "Terminal 5D": 1, "Terminal 5F": 4}, "07:06:51": {"Terminal 2": 1, "Terminal 5D": 2, "Terminal 5F": 5}, "07:08:42": {"Terminal 2": 1, "Terminal 5D": 3, "Terminal 5F": 4}, "07:10:32": {"Terminal 2": 1, "Terminal 5D": 3, "Terminal 5F": 3}, "07:12:21": {"Terminal 2": 1, "Terminal 5D": 2, "Terminal 5F": 3}, "07:14:10": {"Terminal 2": 1, "Terminal 5D": 1, "Terminal 5F": 2}, "07:16:11": {"Terminal 2": 1, "Terminal 5D": 2, "Terminal 5F": 2}, "07:18:00": {"Terminal 2": 1, "Terminal 5D": 2, "Terminal 5F": 2}, "07:19:50": {"Terminal 2": 1, "Terminal 5D": 2, "Terminal 5F": 1}, "07:21:41": {"Terminal 2": 1, "Terminal 5D": 2, "Terminal 5F": 3}, "07:23:30": {"Terminal 2": 1, "Terminal 5D": 2, "Terminal 5F": 3}, "07:25:22": {"Terminal 2": 1, "Terminal 5D": 2, "Terminal 5F": 1}, "07:27:12": {"Terminal 2": 1, "Terminal 5D": 2, "Terminal 5F": 2}, "07:29:01": {"Terminal 2": 1, "Terminal 5D": 2, "Terminal 5F": 4}, "07:30:52": {"Terminal 2": 1, "Terminal 5D": 2, "Terminal 5F": 5}, "07:32:43": {"Terminal 2": 1, "Terminal 5D": 2, "Terminal 5F": 5}, "07:34:35": {"Terminal 2": 1, "Terminal 5D": 2, "Terminal 5F": 5}, "07:36:23": {"Terminal 2": 1, "Terminal 5D": 4, "Terminal 5F": 4}, "07:38:12": {"Terminal 2": 1, "Terminal 5D": 5, "Terminal 5F": 4}, "07:40:02": {"Terminal 2": 1, "Terminal 5D": 4, "Terminal 5F": 7}, "07:41:51": {"Terminal 2": 1, "Terminal 5D": 2, "Terminal 5F": 6}, "07:43:42": {"Terminal 2": 1, "Terminal 5D": 2, "Terminal 5F": 5}, "07:45:33": {"Terminal 2": 1, "Terminal 5D": 3, "Terminal 5F": 5}, "07:47:22": {"Terminal 2": 1, "Terminal 5D": 3, "Terminal 5F": 5}, "07:49:14": {"Terminal 2": 1, "Terminal 5D": 3, "Terminal 5F": 5}, "07:51:05": {"Terminal 2": 1, "Terminal 5D": 3, "Terminal 5F": 5}, "07:52:57": {"Terminal 2": 1, "Terminal 5D": 2, "Terminal 5F": 5}, "07:54:47": {"Terminal 2": 1, "Terminal 5D": 2, "Terminal 5F": 4}, "07:56:37": {"Terminal 2": 1, "Terminal 5D": 2, "Terminal 5F": 4}, "07:58:26": {"Terminal 2": 1, "Terminal 5D": 2, "Terminal 5F": 5}, "08:00:16": {"Terminal 2": 1, "Terminal 5D": 2, "Terminal 5F": 7}, "08:02:06": {"Terminal 2": 1, "Terminal 5D": 2, "Terminal 5F": 6}, "08:03:56": {"Terminal 2": 1, "Terminal 5D": 1, "Terminal 5F": 7}, "08:05:44": {"Terminal 2": 1, "Terminal 5D": 4, "Terminal 5F": 6}, "08:07:32": {"Terminal 2": 1, "Terminal 5D": 4, "Terminal 5F": 6}, "08:09:19": {"Terminal 2": 1, "Terminal 5D": 4, "Terminal 5F": 4}, "08:11:09": {"Terminal 2": 1, "Terminal 5D": 3, "Terminal 5F": 5}, "08:13:00": {"Terminal 2": 1, "Terminal 5D": 4, "Terminal 5F": 6}, "08:14:50": {"Terminal 2": 1, "Terminal 5D": 4, "Terminal 5F": 5}, "08:16:39": {"Terminal 2": 1, "Terminal 5D": 4, "Terminal 5F": 5}, "08:18:29": {"Terminal 2": 1, "Terminal 5D": 4, "Terminal 5F": 4}, "08:20:20": {"Terminal 2": 1, "Terminal 5D": 3, "Terminal 5F": 3}, "08:22:10": {"Terminal 2": 2, "Terminal 5D": 3, "Terminal 5F": 3}, "08:24:02": {"Terminal 2": 2, "Terminal 5D": 4, "Terminal 5F": 3}, "08:25:52": {"Terminal 2": 2, "Terminal 5D": 4, "Terminal 5F": 4}, "08:27:43": {"Terminal 2": 2, "Terminal 5D": 5, "Terminal 5F": 5}, "08:29:33": {"Terminal 2": 1, "Terminal 5D": 4, "Terminal 5F": 5}, "08:31:26": {"Terminal 2": 1, "Terminal 5D": 3, "Terminal 5F": 7}, "08:33:16": {"Terminal 2": 1, "Terminal 5D": 4, "Terminal 5F": 7}, "08:35:07": {"Terminal 2": 1, "Terminal 5D": 5, "Terminal 5F": 6}, "08:36:57": {"Terminal 2": 1, "Terminal 5D": 5, "Terminal 5F": 7}, "08:38:46": {"Terminal 2": 2, "Terminal 5D": 4, "Terminal 5F": 7}, "08:40:35": {"Terminal 2": 1, "Terminal 5D": 5, "Terminal 5F": 4}, "08:42:25": {"Terminal 2": 2, "Terminal 5D": 5, "Terminal 5F": 4}, "08:44:15": {"Terminal 2": 1, "Terminal 5D": 5, "Terminal 5F": 5}, "08:46:06": {"Terminal 2": 1, "Terminal 5D": 3, "Terminal 5F": 5}, "08:47:56": {"Terminal 2": 1, "Terminal 5D": 2, "Terminal 5F": 4}, "08:49:51": {"Terminal 2": 1, "Terminal 5D": 2, "Terminal 5F": 5}, "08:51:40": {"Terminal 2": 1, "Terminal 5D": 2, "Terminal 5F": 5}, "08:53:30": {"Terminal 2": 1, "Terminal 5D": 3, "Terminal 5F": 6}, "08:55:19": {"Terminal 2": 1, "Terminal 5D": 4, "Terminal 5F": 6}, "08:57:09": {"Terminal 2": 1, "Terminal 5D": 5, "Terminal 5F": 6}, "08:59:00": {"Terminal 2": 1, "Terminal 5D": 6, "Terminal 5F": 9}, "09:00:53": {"Terminal 2": 1, "Terminal 5D": 7, "Terminal 5F": 10}, "09:02:40": {"Terminal 2": 1, "Terminal 5D": 8, "Terminal 5F": 7}, "09:04:30": {"Terminal 2": 1, "Terminal 5D": 8, "Terminal 5F": 8}, "09:06:20": {"Terminal 2": 1, "Terminal 5D": 8, "Terminal 5F": 8}, "09:08:13": {"Terminal 2": 2, "Terminal 5D": 11, "Terminal 5F": 10}, "09:10:02": {"Terminal 2": 2, "Terminal 5D": 12, "Terminal 5F": 12}, "09:11:55": {"Terminal 2": 2, "Terminal 5D": 9, "Terminal 5F": 14}, "09:13:46": {"Terminal 2": 1, "Terminal 5D": 9, "Terminal 5F": 11}, "09:15:35": {"Terminal 2": 1, "Terminal 5D": 8, "Terminal 5F": 11}, "09:17:26": {"Terminal 2": 1, "Terminal 5D": 8, "Terminal 5F": 9}, "09:19:17": {"Terminal 2": 3, "Terminal 5D": 9, "Terminal 5F": 10}, "09:21:07": {"Terminal 2": 2, "Terminal 5D": 11, "Terminal 5F": 13}, "09:22:58": {"Terminal 2": 1, "Terminal 5D": 13, "Terminal 5F": 11}, "09:24:50": {"Terminal 2": 1, "Terminal 5D": 12, "Terminal 5F": 12}, "09:26:44": {"Terminal 2": 2, "Terminal 5D": 15, "Terminal 5F": 10}, "09:28:33": {"Terminal 2": 3, "Terminal 5D": 16, "Terminal 5F": 10}, "09:30:25": {"Terminal 2": 3, "Terminal 5D": 14, "Terminal 5F": 10}, "09:32:18": {"Terminal 2": 3, "Terminal 5D": 16, "Terminal 5F": 9}, "09:34:10": {"Terminal 2": 2, "Terminal 5D": 18, "Terminal 5F": 12}, "09:36:01": {"Terminal 2": 1, "Terminal 5D": 20, "Terminal 5F": 12}, "09:37:51": {"Terminal 2": 1, "Terminal 5D": 19, "Terminal 5F": 10}, "09:39:42": {"Terminal 2": 1, "Terminal 5D": 19, "Terminal 5F": 45}, "09:41:32": {"Terminal 2": 1, "Terminal 5D": 20, "Terminal 5F": 15}, "09:43:22": {"Terminal 2": 1, "Terminal 5D": 13, "Terminal 5F": 14}, "09:45:10": {"Terminal 2": 2, "Terminal 5D": 10, "Terminal 5F": 13}, "09:47:02": {"Terminal 2": 5, "Terminal 5D": 10, "Terminal 5F": 14}, "09:48:53": {"Terminal 2": 6, "Terminal 5D": 13, "Terminal 5F": 19}, "09:50:43": {"Terminal 2": 8, "Terminal 5D": 14, "Terminal 5F": 19}, "09:52:38": {"Terminal 2": 7, "Terminal 5D": 11, "Terminal 5F": 13}}